did_it_spill/__init__.py
did_it_spill/main.py
did_it_spill/numpy_spills.py
did_it_spill/semantic_similarity.py
tests/__init__.py
tests/test_main.py
did_it_spill-1.0.3.dist-info/LICENSE
did_it_spill-1.0.3.dist-info/METADATA
did_it_spill-1.0.3.dist-info/WHEEL
did_it_spill-1.0.3.dist-info/top_level.txt
did_it_spill-1.0.3.dist-info/RECORD
