Metadata-Version: 2.1
Name: did-it-spill
Version: 1.0.3
Summary: Checks if you have data from train set in your test set
Author: LaihoE
License: UNKNOWN
Platform: UNKNOWN
License-File: LICENSE
Requires-Dist: numpy
Requires-Dist: torch
Requires-Dist: torchvision
